{"cameraMode":{"drawMode":0,"name":"Shaded","section":"Shading Mode"},"sceneLighting":false,"audioPlay":false,"sceneViewState":{"m_AlwaysRefresh":false,"showFog":true,"showSkybox":false,"showFlares":true,"showImageEffects":true,"showParticleSystems":true,"showVisualEffectGraphs":true,"m_FxEnabled":true},"in2DMode":false,"pivot":{"x":-9.940207481384278,"y":-3.490468740463257,"z":-1.6416115760803223},"rotation":{"x":-0.11230574548244477,"y":0.8284702301025391,"z":-0.17945188283920289,"w":-0.5184849500656128},"size":6.764766216278076,"orthographic":false}